finlogic-0.6.3.dist-info/METADATA
finlogic-0.6.3.dist-info/WHEEL
finlogic-0.6.3.dist-info/licenses/LICENSE
finlogic/__init__.py
finlogic/company.py
finlogic/data.py
finlogic/indicators.py
finlogic-0.6.3.dist-info/RECORD
