Metadata-Version: 2.1
Name: FinLogic
Version: 0.6.3
Summary: Finance toolkit for listed Brazilian companies
Keywords: pandas, cvm, finance, investment, accounting
Author-Email: Carlos Carvalho <cr.cj@outlook.com>
License: MIT License
Classifier: Topic :: Office/Business :: Financial :: Accounting
Classifier: Topic :: Office/Business :: Financial :: Investment
Classifier: Programming Language :: Python :: 3.10
Classifier: Programming Language :: Python :: 3.11
Classifier: Programming Language :: Python :: 3.12
Project-URL: Repository, https://github.com/crdcj/FinLogic
Requires-Python: >=3.10
Requires-Dist: pandas>=2.0.0
Requires-Dist: pytest>=8.0.0; extra == "dev"
Requires-Dist: ipykernel>=6.0.0; extra == "dev"
Provides-Extra: dev
